forkast_py_client/__init__.py
forkast_py_client/abi/ConditionalTokens.abi.json
forkast_py_client/abi/GnosisSafe.abi.json
forkast_py_client/abi/MultiSend.abi.json
forkast_py_client/abi/PCToken.abi.json
forkast_py_client/config/__init__.py
forkast_py_client/config/constants.py
forkast_py_client/mappers/__init__.py
forkast_py_client/mappers/account_mapper.py
forkast_py_client/mappers/balances_mapper.py
forkast_py_client/mappers/market_mapper.py
forkast_py_client/mappers/order_mapper.py
forkast_py_client/services/__init__.py
forkast_py_client/services/account.py
forkast_py_client/services/balances.py
forkast_py_client/services/base.py
forkast_py_client/services/market.py
forkast_py_client/services/order.py
forkast_py_client/types/__init__.py
forkast_py_client/types/accounts.py
forkast_py_client/types/balances.py
forkast_py_client/types/market.py
forkast_py_client/types/orders.py
forkast_py_client/utils/__init__.py
forkast_py_client/utils/abi_loader.py
forkast_py_client/utils/provider.py
forkast_py_client-0.1.0.dist-info/licenses/LICENSE
forkast_py_client-0.1.0.dist-info/METADATA
forkast_py_client-0.1.0.dist-info/WHEEL
forkast_py_client-0.1.0.dist-info/RECORD
