Metadata-Version: 2.4
Name: forkast-py-client
Version: 0.1.0
Summary: Python client for the Forkast Orderbooks
License-Expression: MIT
License-File: LICENSE
Author: Forkast
Author-email: tech@forkast.gg
Requires-Python: >=3.12
Classifier: Programming Language :: Python :: 3
Classifier: Programming Language :: Python :: 3.12
Classifier: Programming Language :: Python :: 3.13
Classifier: Programming Language :: Python :: 3.14
Requires-Dist: eth-account (>=0.10.0,<0.11.0)
Requires-Dist: python-dotenv (>=1.0.1,<2.0.0)
Requires-Dist: requests (>=2.31.0,<3.0.0)
Requires-Dist: web3 (>=6.15.1,<7.0.0)
